.gitignore
LICENSE
MANIFEST.in
README.md
requirements-dev.txt
requirements.txt
setup.py
.buildkite/pipeline.yml
shudder/__init__.py
shudder/__main__.py
shudder/config.py
shudder/metadata.py
shudder/queue.py
shudder.egg-info/PKG-INFO
shudder.egg-info/SOURCES.txt
shudder.egg-info/dependency_links.txt
shudder.egg-info/requires.txt
shudder.egg-info/top_level.txt
tests/shudder/.gitkeep