Metadata-Version: 1.0
Name: shudder
Version: 0.2.0
Summary: Graceful shutdowns using autoscaling lifecycle hooks.
Home-page: https://github.com/scopely/shudder
Author: Anthony Grimes
Author-email: anthony@scopely.com
License: Apache 2.0
Platform: UNKNOWN
